odoo9_addon_web_ir_actions_act_window_message-9.0.1.0.0.99.dev5-py2.7-nspkg.pth
odoo9_addon_web_ir_actions_act_window_message-9.0.1.0.0.99.dev5.dist-info/DESCRIPTION.rst
odoo9_addon_web_ir_actions_act_window_message-9.0.1.0.0.99.dev5.dist-info/METADATA
odoo9_addon_web_ir_actions_act_window_message-9.0.1.0.0.99.dev5.dist-info/RECORD
odoo9_addon_web_ir_actions_act_window_message-9.0.1.0.0.99.dev5.dist-info/WHEEL
odoo9_addon_web_ir_actions_act_window_message-9.0.1.0.0.99.dev5.dist-info/metadata.json
odoo9_addon_web_ir_actions_act_window_message-9.0.1.0.0.99.dev5.dist-info/namespace_packages.txt
odoo9_addon_web_ir_actions_act_window_message-9.0.1.0.0.99.dev5.dist-info/top_level.txt
odoo_addons/web_ir_actions_act_window_message/README.rst
odoo_addons/web_ir_actions_act_window_message/__init__.py
odoo_addons/web_ir_actions_act_window_message/__openerp__.py
odoo_addons/web_ir_actions_act_window_message/i18n/ar.po
odoo_addons/web_ir_actions_act_window_message/i18n/de.po
odoo_addons/web_ir_actions_act_window_message/i18n/es.po
odoo_addons/web_ir_actions_act_window_message/i18n/eu.po
odoo_addons/web_ir_actions_act_window_message/i18n/fi.po
odoo_addons/web_ir_actions_act_window_message/i18n/fr.po
odoo_addons/web_ir_actions_act_window_message/i18n/hr.po
odoo_addons/web_ir_actions_act_window_message/i18n/it.po
odoo_addons/web_ir_actions_act_window_message/i18n/nl.po
odoo_addons/web_ir_actions_act_window_message/i18n/pt_BR.po
odoo_addons/web_ir_actions_act_window_message/i18n/sl.po
odoo_addons/web_ir_actions_act_window_message/i18n/tr.po
odoo_addons/web_ir_actions_act_window_message/static/description/icon.png
odoo_addons/web_ir_actions_act_window_message/static/src/js/web_ir_actions_act_window_message.js
odoo_addons/web_ir_actions_act_window_message/static/src/xml/web_ir_actions_act_window_message.xml
odoo_addons/web_ir_actions_act_window_message/views/templates.xml
