Metadata-Version: 2.0
Name: odoo9-addon-web-ir-actions-act-window-message
Version: 9.0.1.0.0.99.dev5
Summary: Show a message box to users
Home-page: UNKNOWN
Author: Therp BV, ACSONE SA/NV, Odoo Community Association (OCA)
Author-email: support@odoo-community.org
License: AGPL-3
Platform: UNKNOWN
Classifier: Programming Language :: Python :: 2.7
Classifier: Framework :: Odoo
Classifier: License :: OSI Approved :: GNU Affero General Public License v3
Requires-Dist: odoo (<9.1a,>=9.0a)
